setup.py
thumbor_ceph/__init__.py
thumbor_ceph.egg-info/PKG-INFO
thumbor_ceph.egg-info/SOURCES.txt
thumbor_ceph.egg-info/dependency_links.txt
thumbor_ceph.egg-info/not-zip-safe
thumbor_ceph.egg-info/top_level.txt
thumbor_ceph/result_storages/__init__.py
thumbor_ceph/result_storages/ceph_storage.py
thumbor_ceph/storages/__init__.py
thumbor_ceph/storages/ceph_storage.py