Metadata-Version: 1.1
Name: thumbor-ceph
Version: 1
Summary: Thumbor Ceph Rados extensions
Home-page: UNKNOWN
Author: Laurent Barbe
Author-email: laurent@ksperis.com
License: UNKNOWN
Platform: UNKNOWN
Requires: thumbor
